certilizer/__init__.py
certilizer/cert.py
certilizer/logger.py
certilizer/reporter.py
certilizer-2.1.0.dist-info/METADATA
certilizer-2.1.0.dist-info/WHEEL
certilizer-2.1.0.dist-info/entry_points.txt
certilizer-2.1.0.dist-info/licenses/LICENSE
certilizer-2.1.0.dist-info/RECORD
