Metadata-Version: 2.4
Name: certilizer
Version: 2.1.0
Summary: Generate report of SSL/TLS certificates from a list of endpoints defined in a YAML configuration file
License: Apache-2.0
License-File: LICENSE
Keywords: certilizer,report,ssl,tls,certificate
Author: Cliffano Subagio
Author-email: cliffano@gmail.com
Requires-Python: >=3.10,<4.0
Classifier: License :: OSI Approved :: Apache Software License
Classifier: Operating System :: OS Independent
Classifier: Programming Language :: Python :: 3
Classifier: Programming Language :: Python :: 3.10
Classifier: Programming Language :: Python :: 3.11
Classifier: Programming Language :: Python :: 3.12
Classifier: Programming Language :: Python :: 3.13
Classifier: Programming Language :: Python :: 3.14
Requires-Dist: cfgrw (>=1.0.0,<1.1.0)
Requires-Dist: click (>=8.3.1,<8.4.0)
Requires-Dist: conflog (>=2.1.0,<2.2.0)
Requires-Dist: pandas (>=2.3.3,<2.4.0)
Requires-Dist: pandasreporter (>=1.0.0,<1.1.0)
Project-URL: Documentation, https://github.com/cliffano/certilizer
Project-URL: Homepage, https://github.com/cliffano/certilizer
Project-URL: Repository, https://github.com/cliffano/certilizer
